lightmem/__init__.py
lightmem/memory/__init__.py
lightmem/memory/graph.py
lightmem/memory/lightmem.py
lightmem/memory/prompts.py
lightmem/memory/t2p.py
lightmem/memory/utils.py
lightmem/pre_settings/__init__.py
lightmem/pre_settings/base.py
lightmem/pre_settings/llms/__init__.py
lightmem/pre_settings/llms/base.py
lightmem/pre_settings/llms/deepseek.py
lightmem/pre_settings/llms/factory.py
lightmem/pre_settings/text_embedder/__init__.py
lightmem/pre_settings/text_embedder/base.py
lightmem/pre_settings/text_embedder/factory.py
lightmem/pre_settings/text_embedder/huggingface.py
lightmem/pre_settings/vector_stores/__init__.py
lightmem/pre_settings/vector_stores/base.py
lightmem/pre_settings/vector_stores/factory.py
lightmem/pre_settings/vector_stores/langchain.py
lightmem-0.0.0.dist-info/METADATA
lightmem-0.0.0.dist-info/WHEEL
lightmem-0.0.0.dist-info/top_level.txt
lightmem-0.0.0.dist-info/RECORD
