Metadata-Version: 2.1
Name: lightmem
Version: 0.0.0
Summary: A light agent memory
Home-page: https://github.com/zjunlp/LightMem
Author: Jizhan fang
Author-email: fangjizhan@zju.edu.cn
Classifier: Programming Language :: Python :: 3
Classifier: License :: OSI Approved :: MIT License
Requires-Python: >=3.6
